firestealer/__init__.py
firestealer/_charm.py
firestealer/_cmd.py
firestealer/_exceptions.py
firestealer/_fsteal.py
firestealer/_influx.py
firestealer/_prometheus.py
firestealer-0.5.0.dist-info/METADATA
firestealer-0.5.0.dist-info/RECORD
firestealer-0.5.0.dist-info/WHEEL
firestealer-0.5.0.dist-info/entry_points.txt
firestealer-0.5.0.dist-info/top_level.txt
