Metadata-Version: 2.1
Name: firestealer
Version: 0.5.0
Summary: A command line tool for parsing Prometheus metrics
Home-page: https://github.com/juju/firestealer
Author: Canonical JAAS Team
Author-email: jaas@canonical.com
License: UNKNOWN
Keywords: prometheus influxdb metrics charm cli
Platform: UNKNOWN
Classifier: Development Status :: 4 - Beta
Classifier: Intended Audience :: Developers
Classifier: Topic :: Database
Classifier: Topic :: Software Development :: Build Tools
Classifier: License :: OSI Approved :: GNU Lesser General Public License v3 (LGPLv3)
Classifier: Programming Language :: Python :: 3
Classifier: Programming Language :: Python :: 3.5
Classifier: Programming Language :: Python :: 3.6
Requires-Dist: influxdb
Requires-Dist: prometheus-client
